nowcasting_datamodel/__init__.py
nowcasting_datamodel/connection.py
nowcasting_datamodel/fake.py
nowcasting_datamodel/national.py
nowcasting_datamodel/utils.py
nowcasting_datamodel/migrations/__init__.py
nowcasting_datamodel/migrations/app.py
nowcasting_datamodel/models/__init__.py
nowcasting_datamodel/models/api.py
nowcasting_datamodel/models/base.py
nowcasting_datamodel/models/convert.py
nowcasting_datamodel/models/forecast.py
nowcasting_datamodel/models/gsp.py
nowcasting_datamodel/models/metric.py
nowcasting_datamodel/models/models.py
nowcasting_datamodel/models/pv.py
nowcasting_datamodel/models/utils.py
nowcasting_datamodel/read/__init__.py
nowcasting_datamodel/read/read.py
nowcasting_datamodel/read/read_gsp.py
nowcasting_datamodel/read/read_metric.py
nowcasting_datamodel/read/read_models.py
nowcasting_datamodel/read/read_pv.py
nowcasting_datamodel/read/read_user.py
nowcasting_datamodel/save/__init__.py
nowcasting_datamodel/save/adjust.py
nowcasting_datamodel/save/save.py
nowcasting_datamodel/save/update.py
nowcasting_datamodel-1.7.5.dist-info/METADATA
nowcasting_datamodel-1.7.5.dist-info/WHEEL
nowcasting_datamodel-1.7.5.dist-info/top_level.txt
nowcasting_datamodel-1.7.5.dist-info/RECORD
