Metadata-Version: 2.4
Name: nowcasting_datamodel
Version: 1.7.5
Summary: Data Model for the OCF nowcasting project
Home-page: https://github.com/openclimatefix/nowcasting_datamodel
Author: Peter Dudfield
Author-email: peter@openclimatefix.org
License: MIT
Keywords: SQL,Datamodel
Requires-Dist: pydantic==2.5.3
Requires-Dist: pandas
Requires-Dist: sqlalchemy>=2.0
Requires-Dist: psycopg2-binary
Requires-Dist: alembic
Requires-Dist: click
Requires-Dist: freezegun
Requires-Dist: structlog
Requires-Dist: numpy==2.0.0
Dynamic: author
Dynamic: author-email
Dynamic: description
Dynamic: description-content-type
Dynamic: home-page
Dynamic: keywords
Dynamic: license
Dynamic: requires-dist
Dynamic: summary
